_rizin.cpython-311-x86_64-linux-musl.so
rz_bindings_jeng-0.6.0.data/purelib/rizin.py
rz_bindings_jeng-0.6.0.dist-info/RECORD
rz_bindings_jeng-0.6.0.dist-info/METADATA
rz_bindings_jeng-0.6.0.dist-info/WHEEL
rz_bindings_jeng.libs/librz_diff-edb81228.so.0.9.0
rz_bindings_jeng.libs/librz_cons-fa07d90b.so.0.9.0
rz_bindings_jeng.libs/librz_type-72ad4823.so.0.9.0
rz_bindings_jeng.libs/librz_lang-b8ce6340.so.0.9.0
rz_bindings_jeng.libs/librz_flag-58c963a9.so.0.9.0
rz_bindings_jeng.libs/librz_search-af2170a4.so.0.9.0
rz_bindings_jeng.libs/libstdc++-0d31ccbe.so.6.0.32
rz_bindings_jeng.libs/librz_reg-23bdec2f.so.0.9.0
rz_bindings_jeng.libs/librz_syscall-ab744a74.so.0.9.0
rz_bindings_jeng.libs/librz_config-037a3040.so.0.9.0
rz_bindings_jeng.libs/librz_io-58ead473.so.0.9.0
rz_bindings_jeng.libs/librz_debug-fbd9d5d1.so.0.9.0
rz_bindings_jeng.libs/librz_util-c120b8e0.so.0.9.0
rz_bindings_jeng.libs/librz_sign-4b2f72f2.so.0.9.0
rz_bindings_jeng.libs/librz_magic-4169a168.so.0.9.0
rz_bindings_jeng.libs/librz_crypto-b26356a2.so.0.9.0
rz_bindings_jeng.libs/librz_demangler-3b255ccc.so.0.9.0
rz_bindings_jeng.libs/librz_il-46eb5f07.so.0.9.0
rz_bindings_jeng.libs/librz_bin-5dab912d.so.0.9.0
rz_bindings_jeng.libs/librz_hash-b98c2ee6.so.0.9.0
rz_bindings_jeng.libs/libbz2-6dc21a2d.so.1.0.8
rz_bindings_jeng.libs/librz_core-b4a4f03f.so.0.9.0
rz_bindings_jeng.libs/libgcc_s-a0b57c20.so.1
rz_bindings_jeng.libs/librz_arch-d00e9d63.so.0.9.0
rz_bindings_jeng.libs/librz_egg-e000536d.so.0.9.0
rz_bindings_jeng.libs/librz_socket-bd51b59e.so.0.9.0
